timeutilities.py
timeutilities-1.2.dist-info/METADATA
timeutilities-1.2.dist-info/WHEEL
timeutilities-1.2.dist-info/top_level.txt
timeutilities-1.2.dist-info/RECORD
