Metadata-Version: 2.1
Name: timeutilities
Version: 1.2
Summary: Minimal utilities for time managements and manipulation
Home-page: https://github.com/astraldev/timeutilities
Author: astraldev
Author-email: ekureedem480@gmail.com
License: MIT
Requires-Python: >=3
